deci_platform_client/__init__.py
deci_platform_client/api_client.py
deci_platform_client/configuration.py
deci_platform_client/exceptions.py
deci_platform_client/rest.py
deci_platform_client/schemas.py
deci_platform_client/apis/__init__.py
deci_platform_client/apis/path_to_api.py
deci_platform_client/apis/tag_to_api.py
deci_platform_client/apis/paths/__init__.py
deci_platform_client/apis/paths/architectures.py
deci_platform_client/apis/paths/architectures_user.py
deci_platform_client/apis/paths/auth_logout.py
deci_platform_client/apis/paths/autonac_model_name_file_name.py
deci_platform_client/apis/paths/autonac_run_id.py
deci_platform_client/apis/paths/autonac_runs_complete_autonac_run_id.py
deci_platform_client/apis/paths/autonac_runs_start.py
deci_platform_client/apis/paths/companies_stats.py
deci_platform_client/apis/paths/conversion_model_id.py
deci_platform_client/apis/paths/events_.py
deci_platform_client/apis/paths/events_buy_model.py
deci_platform_client/apis/paths/events_compare_models_in_model_zoo.py
deci_platform_client/apis/paths/events_quota_increase.py
deci_platform_client/apis/paths/events_request_public_architecture.py
deci_platform_client/apis/paths/events_support.py
deci_platform_client/apis/paths/events_type.py
deci_platform_client/apis/paths/events_upgrade.py
deci_platform_client/apis/paths/experiments_.py
deci_platform_client/apis/paths/experiments_counter.py
deci_platform_client/apis/paths/experiments_experiment_id_upload_url.py
deci_platform_client/apis/paths/global_configuration_accuracy_metrics.py
deci_platform_client/apis/paths/global_configuration_architectures.py
deci_platform_client/apis/paths/global_configuration_batch_sizes.py
deci_platform_client/apis/paths/global_configuration_deep_learning_tasks.py
deci_platform_client/apis/paths/global_configuration_feature_flags.py
deci_platform_client/apis/paths/global_configuration_frameworks.py
deci_platform_client/apis/paths/global_configuration_hardware.py
deci_platform_client-7.20.0.dist-info/LICENSE.txt
deci_platform_client-7.20.0.dist-info/METADATA
deci_platform_client-7.20.0.dist-info/WHEEL
deci_platform_client-7.20.0.dist-info/top_level.txt
deci_platform_client-7.20.0.dist-info/RECORD
