Metadata-Version: 2.1
Name: deci-platform-client
Version: 7.20.0
Summary: Deci Platform SDK
Home-page: UNKNOWN
Author: Deci AI
Author-email: rnd@deci.ai
License: UNKNOWN
Keywords: Deci,DeciAI,Platform
Platform: UNKNOWN
Requires-Python: >=3.7
License-File: LICENSE.txt
Requires-Dist: certifi (>=14.5.14)
Requires-Dist: frozendict (~=2.3.4)
Requires-Dist: python-dateutil (~=2.8.2)
Requires-Dist: setuptools (>=65.5.1)
Requires-Dist: typing-extensions (~=4.8.0)
Requires-Dist: urllib3 (~=1.26.7)
Requires-Dist: arrow (>=1.2.3)
Requires-Dist: PyJWT (>=2.4.0)
Requires-Dist: requests (>=2.27.1)
Requires-Dist: tqdm (~=4.64)
Requires-Dist: tenacity (~=8.2.2)
